[
{"name":"flare.ParksOffice.Ron Swanson","size":3938,"imports":["flare.PawneeGovt.Mayor Gunderson","flare.family.Wendy Haverford","flare.Tammies.Tammy 1","flare.Tammies.Tammy 2","flare.miniHorses.Lil' Sebastian"]},
{"name":"flare.ParksOffice.Leslie Knope","size":4218,"imports":["flare.ParksOffice.Ron Swanson","flare.PawneeGovt.Marlene Griggs-Knope","flare.miniHorses.Lil' Sebastian","flare.Federal Government.Joe Biden"]},
{"name":"flare.ParksOffice.Tom Haverford","size":4218,"imports":["flare.ParksOffice.Ron Swanson","flare.ParksOffice.Leslie Knope","flare.family.Wendy Haverford","flare.Sapersteins.Jean-Ralphio Saperstein","flare.Sapersteins.Mona-Lisa Saperstein","flare.Sapersteins.Dr Saperstein","flare.miniHorses.Lil' Sebastian"]},
{"name":"flare.ParksOffice.April Ludgate","size":4218,"imports":["flare.ParksOffice.Ron Swanson","flare.ParksOffice.Leslie Knope","flare.miniHorses.Lil' Sebastian"]},
{"name":"flare.ParksOffice.Andy Dwyer","size":4218,"imports":["flare.ParksOffice.Ron Swanson","flare.ParksOffice.Leslie Knope","flare.ParksOffice.April Ludgate","flare.ParksOffice.Tom Haverford","flare.miniHorses.Lil' Sebastian","flare.PawneeGovt.Ethel Beavers"]},
{"name":"flare.ParksOffice.Donna Meegle","size":4218,"imports":["flare.miniHorses.Lil' Sebastian"]},
{"name":"flare.ParksOffice.Jerry Gergich","size":4218,"imports":["flare.ParksOffice.Ron Swanson","flare.ParksOffice.Leslie Knope","flare.ParksOffice.Tom Haverford","flare.ParksOffice.April Ludgate","flare.ParksOffice.Donna Meegle","flare.miniHorses.Lil' Sebastian"]},
{"name":"flare.ParksOffice.Ben Wyatt","size":4218,"imports":["flare.ParksOffice.Leslie Knope","flare.ParksOffice.Chris Traeger"]},
{"name":"flare.ParksOffice.Chris Traeger","size":4218,"imports":["flare.ParksOffice.Leslie Knope","flare.miniHorses.Lil' Sebastian"]},
{"name":"flare.ParksOffice.Ann Perkins","size":4218,"imports":["flare.ParksOffice.Leslie Knope","flare.ParksOffice.Chris Traeger","flare.miniHorses.Lil' Sebastian","flare.ParksOffice.Mark Brendanawicz","flare.radio personalities.The Douche"]},
{"name":"flare.PawneeGovt.Jeremy Jamm","size":4218,"imports":["flare.miniHorses.Lil' Sebastian"]},
{"name":"flare.PawneeGovt.Mayor Gunderson","size":4218,"imports":["flare.miniHorses.Lil' Sebastian"]},
{"name":"flare.PawneeGovt.Marlene Griggs-Knope","size":4218,"imports":["flare.miniHorses.Lil' Sebastian"]},
{"name":"flare.Tammies.Tammy 1","size":4218,"imports":["flare.miniHorses.Lil' Sebastian"]},
{"name":"flare.Tammies.Tammy 2","size":4218,"imports":["flare.miniHorses.Lil' Sebastian"]},
{"name":"flare.Sapersteins.Mona-Lisa Saperstein","size":4218,"imports":["flare.miniHorses.Lil' Sebastian"]},
{"name":"flare.Sapersteins.Jean-Ralphio Saperstein","size":4218,"imports":["flare.miniHorses.Lil' Sebastian"]},
{"name":"flare.Sapersteins.Mona-Lisa Saperstein","size":4218,"imports":["flare.miniHorses.Lil' Sebastian"]},
{"name":"flare.Sapersteins.Dr Saperstein","size":4218,"imports":["flare.miniHorses.Lil' Sebastian"]},
{"name":"flare.miniHorses.Lil' Sebastian","size":4218,"imports":[]},
{"name":"flare.ParksOffice.Mark Brendanawicz","size":4218,"imports":[]},
{"name":"flare.family.Wendy Haverford","size":4218,"imports":[]},
{"name":"flare.PawneeGovt.Bill Dexhart","size":4218,"imports":[]},
{"name":"flare.PawneeGovt.Ken Hotate","size":4218,"imports":[]},
{"name":"flare.PawneeGovt.Ethel Beavers","size":4218,"imports":[]},
{"name":"flare.radio personalities.Crazy Ira","size":4218,"imports":["flare.radio personalities.The Douche"]},
{"name":"flare.radio personalities.The Douche","size":4218,"imports":[]},
{"name":"flare.Federal Government.Joe Biden","size":4218,"imports":[]},
{"name":"flare.Federal Government.John McCAin","size":4218,"imports":[]},
{"name":"flare.Pawnee Services.Joe Fantringham","size":4218,"imports":[]},
{"name":"flare.Pawnee Services.Harris","size":4218,"imports":["flare.Pawnee Services.Brett"]},
{"name":"flare.Pawnee Services.Brett","size":4218,"imports":[]}




]